README.txt
setup.py
mml/__init__.py
mml.egg-info/PKG-INFO
mml.egg-info/SOURCES.txt
mml.egg-info/dependency_links.txt
mml.egg-info/not-zip-safe
mml.egg-info/top_level.txt