Metadata-Version: 1.0
Name: mml
Version: 0.1.0a0
Summary: MML Project developer landmark
Home-page: https://mml.n1sh.com
Author: Nishad
Author-email: nishad@n1sh.com
License: MIT
Platform: UNKNOWN
